rateLimitedQueues.py
rateLimitedQueues-0.0.3.post1.dist-info/METADATA
rateLimitedQueues-0.0.3.post1.dist-info/WHEEL
rateLimitedQueues-0.0.3.post1.dist-info/top_level.txt
rateLimitedQueues-0.0.3.post1.dist-info/RECORD
