Metadata-Version: 2.1
Name: rateLimitedQueues
Version: 0.0.3.post1
Summary: A well maintained program to execute functions in queue as if only 1 worker is executing them one by one (High priority first). Works wonders when a series of time consuming tasks has to be performed but they need to be in sequence.
Maintainer-email: Bhindi <bhaskarpanja93@gmail.com>
Project-URL: Homepage, https://github.com/BhaskarPanja93/rateLimitedQueues
Keywords: thread,threaded,task,threaded task,queue,queues,queued tasks
Classifier: License :: OSI Approved :: MIT License
Classifier: Programming Language :: Python
Classifier: Programming Language :: Python :: 3
Requires-Python: >=3.6
